{
  "module_types": [
    {
      "id": "physical_strike_lv1",
      "name": "物理打撃Lv1",
      "category": "physical_attack",
      "tags": ["physical_low"],
      "base_effect": 10.0,
      "stat_reference": "STR",
      "description": "基本的な物理攻撃。敵に物理ダメージを与える。",
      "cooldown_seconds": 10.0,
      "difficulty": 1,
      "min_drop_level": 1
    },
    {
      "id": "physical_strike_lv2",
      "name": "物理打撃Lv2",
      "category": "physical_attack",
      "tags": ["physical_mid"],
      "base_effect": 25.0,
      "stat_reference": "STR",
      "description": "強化された物理攻撃。敵に中程度の物理ダメージを与える。",
      "cooldown_seconds": 15.0,
      "difficulty": 2,
      "min_drop_level": 10
    },
    {
      "id": "physical_strike_lv3",
      "name": "物理打撃Lv3",
      "category": "physical_attack",
      "tags": ["physical_high"],
      "base_effect": 50.0,
      "stat_reference": "STR",
      "description": "最強の物理攻撃。敵に大ダメージを与える。",
      "cooldown_seconds": 20.0,
      "difficulty": 3,
      "min_drop_level": 20
    },
    {
      "id": "fireball_lv1",
      "name": "ファイアボールLv1",
      "category": "magic_attack",
      "tags": ["magic_low"],
      "base_effect": 12.0,
      "stat_reference": "MAG",
      "description": "炎の魔法弾を放つ。敵に魔法ダメージを与える。",
      "cooldown_seconds": 10.0,
      "difficulty": 1,
      "min_drop_level": 1
    },
    {
      "id": "fireball_lv2",
      "name": "ファイアボールLv2",
      "category": "magic_attack",
      "tags": ["magic_mid"],
      "base_effect": 22.0,
      "stat_reference": "MAG",
      "description": "強力な炎の魔法弾。敵に中程度の魔法ダメージを与える。",
      "cooldown_seconds": 15.0,
      "difficulty": 2,
      "min_drop_level": 10
    },
    {
      "id": "fireball_lv3",
      "name": "ファイアボールLv3",
      "category": "magic_attack",
      "tags": ["magic_high"],
      "base_effect": 40.0,
      "stat_reference": "MAG",
      "description": "灼熱の魔法弾。敵に大魔法ダメージを与える。",
      "cooldown_seconds": 20.0,
      "difficulty": 3,
      "min_drop_level": 20
    },
    {
      "id": "heal_lv1",
      "name": "ヒールLv1",
      "category": "heal",
      "tags": ["heal_low"],
      "base_effect": 8.0,
      "stat_reference": "MAG",
      "description": "自身のHPを少量回復する。",
      "cooldown_seconds": 10.0,
      "difficulty": 1,
      "min_drop_level": 1
    },
    {
      "id": "heal_lv2",
      "name": "ヒールLv2",
      "category": "heal",
      "tags": ["heal_mid"],
      "base_effect": 16.0,
      "stat_reference": "MAG",
      "description": "自身のHPを中程度回復する。",
      "cooldown_seconds": 15.0,
      "difficulty": 2,
      "min_drop_level": 10
    },
    {
      "id": "heal_lv3",
      "name": "ヒールLv3",
      "category": "heal",
      "tags": ["heal_high"],
      "base_effect": 30.0,
      "stat_reference": "MAG",
      "description": "自身のHPを大きく回復する。",
      "cooldown_seconds": 20.0,
      "difficulty": 3,
      "min_drop_level": 20
    },
    {
      "id": "attack_buff_lv1",
      "name": "攻撃バフLv1",
      "category": "buff",
      "tags": ["buff_low"],
      "base_effect": 5.0,
      "stat_reference": "SPD",
      "description": "一時的に攻撃力を上昇させる。",
      "cooldown_seconds": 10.0,
      "difficulty": 1,
      "min_drop_level": 1
    },
    {
      "id": "defense_buff_lv1",
      "name": "防御バフLv1",
      "category": "buff",
      "tags": ["buff_low"],
      "base_effect": 5.0,
      "stat_reference": "MAG",
      "description": "一時的に受けるダメージを軽減する。",
      "cooldown_seconds": 10.0,
      "difficulty": 1,
      "min_drop_level": 1
    },
    {
      "id": "attack_buff_lv2",
      "name": "攻撃バフLv2",
      "category": "buff",
      "tags": ["buff_mid"],
      "base_effect": 10.0,
      "stat_reference": "SPD",
      "description": "攻撃力を大きく上昇させる。",
      "cooldown_seconds": 10.0,
      "difficulty": 2,
      "min_drop_level": 10
    },
    {
      "id": "defense_buff_lv2",
      "name": "防御バフLv2",
      "category": "buff",
      "tags": ["buff_mid"],
      "base_effect": 10.0,
      "stat_reference": "MAG",
      "description": "受けるダメージを大きく軽減する。",
      "cooldown_seconds": 15.0,
      "difficulty": 2,
      "min_drop_level": 10
    },
    {
      "id": "attack_buff_lv3",
      "name": "攻撃バフLv3",
      "category": "buff",
      "tags": ["buff_high"],
      "base_effect": 18.0,
      "stat_reference": "SPD",
      "description": "攻撃力を大幅に上昇させる。",
      "cooldown_seconds": 20.0,
      "difficulty": 3,
      "min_drop_level": 20
    },
    {
      "id": "attack_debuff_lv1",
      "name": "攻撃ダウンLv1",
      "category": "debuff",
      "tags": ["debuff_low"],
      "base_effect": 5.0,
      "stat_reference": "SPD",
      "description": "敵の攻撃力を一時的に低下させる。",
      "cooldown_seconds": 10.0,
      "difficulty": 1,
      "min_drop_level": 1
    },
    {
      "id": "defense_debuff_lv1",
      "name": "防御ダウンLv1",
      "category": "debuff",
      "tags": ["debuff_low"],
      "base_effect": 5.0,
      "stat_reference": "SPD",
      "description": "敵の防御力を一時的に低下させる。",
      "cooldown_seconds": 10.0,
      "difficulty": 1,
      "min_drop_level": 1
    },
    {
      "id": "attack_debuff_lv2",
      "name": "攻撃ダウンLv2",
      "category": "debuff",
      "tags": ["debuff_mid"],
      "base_effect": 10.0,
      "stat_reference": "SPD",
      "description": "敵の攻撃力を大きく低下させる。",
      "cooldown_seconds": 15.0,
      "difficulty": 2,
      "min_drop_level": 10
    },
    {
      "id": "attack_debuff_lv3",
      "name": "攻撃ダウンLv3",
      "category": "debuff",
      "tags": ["debuff_high"],
      "base_effect": 18.0,
      "stat_reference": "SPD",
      "description": "敵の攻撃力を大幅に低下させる。",
      "cooldown_seconds": 20.0,
      "difficulty": 3,
      "min_drop_level": 20
    }
  ]
}
